<?xml version="1.0" encoding="UTF-8"?><items iblockUid="content:mortgage_work_stage"><item><field name="ACTIVE"><value>Y</value></field><field name="ACTIVE_FROM"/><field name="ACTIVE_TO"/><field name="SORT"><value>500</value></field><field name="NAME"><value>Ведущие банки</value></field><field name="PREVIEW_PICTURE"/><field name="PREVIEW_TEXT"><value>«Сбербанк» и&#13;
«Запсибкомбанк»</value></field><field name="PREVIEW_TEXT_TYPE"><value>text</value></field><field name="DETAIL_PICTURE"/><field name="DETAIL_TEXT"/><field name="DETAIL_TEXT_TYPE"><value>text</value></field><field name="CODE"><value>vedushchie-banki</value></field><field name="TAGS"/><field name="XML_ID"><value>174</value></field><field name="IBLOCK_SECTION"/><property name="ICON_SVG"><value>iblock/3b1/3b19989186946f02ab2edc06968b6839.svg</value></property></item><item><field name="ACTIVE"><value>Y</value></field><field name="ACTIVE_FROM"/><field name="ACTIVE_TO"/><field name="SORT"><value>500</value></field><field name="NAME"><value>Бомба</value></field><field name="PREVIEW_PICTURE"/><field name="PREVIEW_TEXT"><value>от 10 %</value></field><field name="PREVIEW_TEXT_TYPE"><value>text</value></field><field name="DETAIL_PICTURE"/><field name="DETAIL_TEXT"/><field name="DETAIL_TEXT_TYPE"><value>text</value></field><field name="CODE"><value>bomba</value></field><field name="TAGS"/><field name="XML_ID"><value>175</value></field><field name="IBLOCK_SECTION"/><property name="ICON_SVG"><value>iblock/3b1/3b19989186946f02ab2edc06968b6839.svg</value></property></item><item><field name="ACTIVE"><value>Y</value></field><field name="ACTIVE_FROM"/><field name="ACTIVE_TO"/><field name="SORT"><value>500</value></field><field name="NAME"><value>Первона взнос</value></field><field name="PREVIEW_PICTURE"/><field name="PREVIEW_TEXT"><value>от 2%</value></field><field name="PREVIEW_TEXT_TYPE"><value>text</value></field><field name="DETAIL_PICTURE"/><field name="DETAIL_TEXT"/><field name="DETAIL_TEXT_TYPE"><value>text</value></field><field name="CODE"><value>pervona-vznos</value></field><field name="TAGS"/><field name="XML_ID"><value>176</value></field><field name="IBLOCK_SECTION"/><property name="ICON_SVG"><value>iblock/3b1/3b19989186946f02ab2edc06968b6839.svg</value></property></item><item><field name="ACTIVE"><value>Y</value></field><field name="ACTIVE_FROM"/><field name="ACTIVE_TO"/><field name="SORT"><value>500</value></field><field name="NAME"><value>Срок</value></field><field name="PREVIEW_PICTURE"/><field name="PREVIEW_TEXT"><value>от 7 до 20 лет</value></field><field name="PREVIEW_TEXT_TYPE"><value>text</value></field><field name="DETAIL_PICTURE"/><field name="DETAIL_TEXT"/><field name="DETAIL_TEXT_TYPE"><value>text</value></field><field name="CODE"><value>srok</value></field><field name="TAGS"/><field name="XML_ID"><value>177</value></field><field name="IBLOCK_SECTION"/><property name="ICON_SVG"><value>iblock/3b1/3b19989186946f02ab2edc06968b6839.svg</value></property></item></items>